gt3x/__init__.py
gt3x/gt3x_functions.py
gt3x/main.py
gt3x-0.1.1.dist-info/LICENSE
gt3x-0.1.1.dist-info/METADATA
gt3x-0.1.1.dist-info/WHEEL
gt3x-0.1.1.dist-info/top_level.txt
gt3x-0.1.1.dist-info/RECORD
