Metadata-Version: 2.1
Name: gt3x
Version: 0.1.1
Summary: A package to read extract raw acceleration data from .gt3x files.
Home-page: https://github.com/muschellij2/gt3x
Author: Shaheen Syed, John Muschelli
Author-email: shaheen.syed@uit.no
License: MIT
Platform: UNKNOWN
Classifier: Programming Language :: Python :: 3
Classifier: License :: OSI Approved :: MIT License
Classifier: Operating System :: OS Independent
Requires-Python: >=3.6
